configcorr/__init__.py
configcorr/max_ent_config_dmcc.py
configcorr/max_ent_config_naive_gradient_descent.py
configcorr-0.0.1.dist-info/METADATA
configcorr-0.0.1.dist-info/RECORD
configcorr-0.0.1.dist-info/WHEEL
configcorr-0.0.1.dist-info/top_level.txt
